logger_master/__init__.py
logger_master/_fluentd_handler.py
logger_master/_mongo_handler.py
logger_master/_redis_handler.py
logger_master/logger.py
logger_master-0.0.3.dist-info/METADATA
logger_master-0.0.3.dist-info/WHEEL
logger_master-0.0.3.dist-info/top_level.txt
logger_master-0.0.3.dist-info/RECORD
