Metadata-Version: 2.1
Name: logger-master
Version: 0.0.3
Summary: A package for pushing serialized error log which generated by loguru to remote storage like mongodb / redis / fluentd
Home-page: https://github.com/chienfeng0719/logger-master
Author: Jimmy Yeh
Author-email: chienfeng0719@hotmail.com
License: UNKNOWN
Platform: UNKNOWN
Classifier: Programming Language :: Python :: 3
Classifier: License :: OSI Approved :: MIT License
Classifier: Operating System :: OS Independent
Requires-Python: >=3.6
Requires-Dist: loguru (==0.5.3)
Requires-Dist: fluent-logger (==0.9.6)
